pytest_speed/__init__.py
pytest_speed/benchmark.py
pytest_speed/cli.py
pytest_speed/save.py
pytest_speed/utils.py
pytest_speed-0.3.5.dist-info/METADATA
pytest_speed-0.3.5.dist-info/WHEEL
pytest_speed-0.3.5.dist-info/entry_points.txt
pytest_speed-0.3.5.dist-info/RECORD
